distbuilder/__init__.py
distbuilder/_version.py
distbuilder/master.py
distbuilder/opy_library.py
distbuilder/pip_installer.py
distbuilder/py_installer.py
distbuilder/qt_cpp.py
distbuilder/qt_installer.py
distbuilder/util.py
distbuilder/qtifw_ui/base.ui
distbuilder/qtifw_ui/finish.ui
distbuilder/qtifw_ui/installationwidget-example.ui
distbuilder/qtifw_ui/introduction.ui
distbuilder/qtifw_ui/licensewidget-example.ui
distbuilder/qtifw_ui/readytoinstall-example.ui
distbuilder/qtifw_ui/readytoinstall.ui
distbuilder/qtifw_ui/simpletext.ui
distbuilder/qtifw_ui/targetdirectory.ui
distbuilder-0.7.8.2.2.dist-info/LICENSE
distbuilder-0.7.8.2.2.dist-info/METADATA
distbuilder-0.7.8.2.2.dist-info/WHEEL
distbuilder-0.7.8.2.2.dist-info/top_level.txt
distbuilder-0.7.8.2.2.dist-info/RECORD
