Metadata-Version: 2.1
Name: distbuilder
Version: 0.7.8.2.2
Summary: Wrapper for other libraries and tools including PyInstaller, the Qt Installer Framework, Opy (a code obfuscater), PIP, and more.
Home-page: https://github.com/BuvinJT/distbuilder
Author: BuvinJ
Author-email: buvintech@gmail.com
License: UNKNOWN
Keywords: distbuilder,dist,distribution,install,package,distutils,setuptools
Platform: UNKNOWN
Classifier: Programming Language :: Python :: 2.7
Classifier: Programming Language :: Python :: 3
Classifier: Operating System :: OS Independent
Classifier: License :: OSI Approved :: GNU General Public License v3 (GPLv3)
Classifier: Intended Audience :: Developers
Classifier: Topic :: Software Development :: Build Tools
Classifier: Natural Language :: English
Classifier: Development Status :: 3 - Alpha
Requires-Dist: six
Requires-Dist: PyInstaller
Requires-Dist: opy-distbuilder
Requires-Dist: argparse
